<annotation>
	<folder></folder>
	<filename>WIN_20221023_15_32_11_Pro_jpg.rf.cabeeb629441a099cc49ca14131dd0ff.jpg</filename>
	<path>WIN_20221023_15_32_11_Pro_jpg.rf.cabeeb629441a099cc49ca14131dd0ff.jpg</path>
	<source>
		<database>roboflow.ai</database>
	</source>
	<size>
		<width>640</width>
		<height>480</height>
		<depth>3</depth>
	</size>
	<segmented>0</segmented>
	<object>
		<name>Incorrect_installation</name>
		<pose>Unspecified</pose>
		<truncated>0</truncated>
		<difficult>0</difficult>
		<occluded>0</occluded>
		<bndbox>
			<xmin>10</xmin>
			<xmax>125</xmax>
			<ymin>168</ymin>
			<ymax>249</ymax>
		</bndbox>
		<polygon>
			<x1>78.52</x1>
			<y1>167.3</y1>
			<x2>79.19</x2>
			<y2>179.96</y2>
			<x3>51.52</x3>
			<y3>193.3</y3>
			<x4>51.52</x4>
			<y4>168.97</y4>
			<x5>8.86</x5>
			<y5>168.97</y5>
			<x6>8.52</x6>
			<y6>224.63</y6>
			<x7>35.19</x7>
			<y7>225.29</y7>
			<x8>46.85</x8>
			<y8>247.96</y8>
			<x9>56.19</x9>
			<y9>245.63</y9>
			<x10>57.52</x10>
			<y10>239.29</y10>
			<x11>90.85</x11>
			<y11>224.29</y11>
			<x12>124.18</x12>
			<y12>224.96</y12>
			<x13>122.18</x13>
			<y13>167.63</y13>
			<x14>78.52</x14>
			<y14>167.3</y14>
		</polygon>
	</object>
	<object>
		<name>Incorrect_installation</name>
		<pose>Unspecified</pose>
		<truncated>0</truncated>
		<difficult>0</difficult>
		<occluded>0</occluded>
		<bndbox>
			<xmin>3</xmin>
			<xmax>89</xmax>
			<ymin>318</ymin>
			<ymax>436</ymax>
		</bndbox>
		<polygon>
			<x1>59.14</x1>
			<y1>434.01</y1>
			<x2>58.38</x2>
			<y2>417.01</y2>
			<x3>74.76</x3>
			<y3>417.84</y3>
			<x4>87.82</x4>
			<y4>409.96</y4>
			<x5>86.44</x5>
			<y5>398.9</y5>
			<x6>81.74</x6>
			<y6>396.9</y6>
			<x7>76.14</x7>
			<y7>349.97</y7>
			<x8>76.14</x8>
			<y8>338.91</y8>
			<x9>73.1</x9>
			<y9>331.93</y9>
			<x10>59.21</x10>
			<y10>328.89</y10>
			<x11>59.21</x11>
			<y11>317.49</y11>
			<x12>2.46</x12>
			<y12>318.45</y12>
			<x13>3.84</x13>
			<y13>360.61</y13>
			<x14>31.49</x14>
			<y14>359.23</y14>
			<x15>37.02</x15>
			<y15>392.41</y15>
			<x16>3.15</x16>
			<y16>389.64</y16>
			<x17>4</x17>
			<y17>434.9</y17>
			<x18>59.14</x18>
			<y18>434.01</y18>
		</polygon>
	</object>
</annotation>
