<annotation>
	<folder></folder>
	<filename>WIN_20221017_19_23_50_Pro_jpg.rf.c2775553cb4279dd69bcf830334f7b99.jpg</filename>
	<path>WIN_20221017_19_23_50_Pro_jpg.rf.c2775553cb4279dd69bcf830334f7b99.jpg</path>
	<source>
		<database>roboflow.ai</database>
	</source>
	<size>
		<width>640</width>
		<height>480</height>
		<depth>3</depth>
	</size>
	<segmented>0</segmented>
	<object>
		<name>Dry_joint</name>
		<pose>Unspecified</pose>
		<truncated>0</truncated>
		<difficult>0</difficult>
		<occluded>0</occluded>
		<bndbox>
			<xmin>333</xmin>
			<xmax>408</xmax>
			<ymin>135</ymin>
			<ymax>215</ymax>
		</bndbox>
		<polygon>
			<x1>399.95</x1>
			<y1>144.33</y1>
			<x2>391.88</x2>
			<y2>137.56</y2>
			<x3>382.5</x3>
			<y3>135.82</y3>
			<x4>368.32</x4>
			<y4>134.29</y4>
			<x5>359.15</x5>
			<y5>136.47</y5>
			<x6>348.24</x6>
			<y6>142.36</y6>
			<x7>341.26</x7>
			<y7>153.93</y7>
			<x8>336.24</x8>
			<y8>162.22</y8>
			<x9>332.32</x9>
			<y9>172.25</y9>
			<x10>337.34</x10>
			<y10>185.12</y10>
			<x11>342.79</x11>
			<y11>193.42</y11>
			<x12>376.83</x12>
			<y12>212.18</y12>
			<x13>381.19</x13>
			<y13>213.71</y13>
			<x14>388.82</x14>
			<y14>213.71</y14>
			<x15>391.66</x15>
			<y15>210.87</y15>
			<x16>398.86</x16>
			<y16>202.36</y16>
			<x17>406.93</x17>
			<y17>158.94</y17>
			<x18>403.66</x18>
			<y18>149.34</y18>
			<x19>399.95</x19>
			<y19>144.33</y19>
		</polygon>
	</object>
	<object>
		<name>Dry_joint</name>
		<pose>Unspecified</pose>
		<truncated>0</truncated>
		<difficult>0</difficult>
		<occluded>0</occluded>
		<bndbox>
			<xmin>480</xmin>
			<xmax>549</xmax>
			<ymin>12</ymin>
			<ymax>79</ymax>
		</bndbox>
		<polygon>
			<x1>533.37</x1>
			<y1>15.53</y1>
			<x2>517.04</x2>
			<y2>10.82</y2>
			<x3>510.13</x3>
			<y3>10.82</y3>
			<x4>496.3</x4>
			<y4>15.22</y4>
			<x5>487.51</x5>
			<y5>24.33</y5>
			<x6>481.54</x6>
			<y6>33.44</y6>
			<x7>479.34</x7>
			<y7>49.15</y7>
			<x8>482.48</x8>
			<y8>61.4</y8>
			<x9>489.39</x9>
			<y9>70.2</y9>
			<x10>503.21</x10>
			<y10>78.05</y10>
			<x11>509.81</x11>
			<y11>78.05</y11>
			<x12>517.67</x12>
			<y12>77.42</y12>
			<x13>527.09</x13>
			<y13>75.54</y13>
			<x14>532.43</x14>
			<y14>72.08</y14>
			<x15>538.72</x15>
			<y15>64.86</y15>
			<x16>546.57</x16>
			<y16>53.86</y16>
			<x17>548.14</x17>
			<y17>46.64</y17>
			<x18>547.83</x18>
			<y18>35.01</y18>
			<x19>542.49</x19>
			<y19>23.07</y19>
			<x20>533.37</x20>
			<y20>15.53</y20>
		</polygon>
	</object>
</annotation>
