<annotation>
	<folder></folder>
	<filename>WIN_20221017_19_24_14_Pro_jpg.rf.f893e3be5545187aca02f1a940558aa6.jpg</filename>
	<path>WIN_20221017_19_24_14_Pro_jpg.rf.f893e3be5545187aca02f1a940558aa6.jpg</path>
	<source>
		<database>roboflow.ai</database>
	</source>
	<size>
		<width>640</width>
		<height>480</height>
		<depth>3</depth>
	</size>
	<segmented>0</segmented>
	<object>
		<name>Dry_joint</name>
		<pose>Unspecified</pose>
		<truncated>0</truncated>
		<difficult>0</difficult>
		<occluded>0</occluded>
		<bndbox>
			<xmin>397</xmin>
			<xmax>464</xmax>
			<ymin>396</ymin>
			<ymax>465</ymax>
		</bndbox>
		<polygon>
			<x1>400.43</x1>
			<y1>409.93</y1>
			<x2>395.72</x2>
			<y2>426.27</y2>
			<x3>395.72</x3>
			<y3>433.18</y3>
			<x4>400.12</x4>
			<y4>447</y4>
			<x5>409.23</x5>
			<y5>455.8</y5>
			<x6>418.34</x6>
			<y6>461.77</y6>
			<x7>434.05</x7>
			<y7>463.97</y7>
			<x8>446.3</x8>
			<y8>460.83</y8>
			<x9>455.1</x9>
			<y9>453.92</y9>
			<x10>462.95</x10>
			<y10>440.09</y10>
			<x11>462.95</x11>
			<y11>433.49</y11>
			<x12>462.32</x12>
			<y12>425.64</y12>
			<x13>460.44</x13>
			<y13>416.21</y13>
			<x14>456.98</x14>
			<y14>410.87</y14>
			<x15>449.76</x15>
			<y15>404.59</y15>
			<x16>438.76</x16>
			<y16>396.74</y16>
			<x17>431.53</x17>
			<y17>395.16</y17>
			<x18>419.91</x18>
			<y18>395.48</y18>
			<x19>407.97</x19>
			<y19>400.82</y19>
			<x20>400.43</x20>
			<y20>409.93</y20>
		</polygon>
	</object>
	<object>
		<name>Dry_joint</name>
		<pose>Unspecified</pose>
		<truncated>0</truncated>
		<difficult>0</difficult>
		<occluded>0</occluded>
		<bndbox>
			<xmin>397</xmin>
			<xmax>471</xmax>
			<ymin>205</ymin>
			<ymax>284</ymax>
		</bndbox>
		<polygon>
			<x1>395.57</x1>
			<y1>281.42</y1>
			<x2>468.45</x2>
			<y2>282.68</y2>
			<x3>470.03</x3>
			<y3>206.96</y3>
			<x4>396.51</x4>
			<y4>204.45</y4>
			<x5>395.57</x5>
			<y5>281.42</y5>
		</polygon>
	</object>
</annotation>
